<?xml version="1.0"?>
<Interface Version="1" Minor="1">
	<Ifc Id="ROOT" Top="1">
		<Bus Id="cam_d">
			<Port Id="0" Dir="IN"/>
			<Port Id="1" Dir="IN"/>
			<Port Id="2" Dir="IN"/>
			<Port Id="3" Dir="IN"/>
			<Port Id="4" Dir="IN"/>
			<Port Id="5" Dir="IN"/>
			<Port Id="6" Dir="IN"/>
			<Port Id="7" Dir="IN"/>
		</Bus>
		<Bus Id="LED">
			<Port Id="0" Dir="OUT"/>
			<Port Id="1" Dir="OUT"/>
			<Port Id="2" Dir="OUT"/>
			<Port Id="3" Dir="OUT"/>
			<Port Id="4" Dir="OUT"/>
			<Port Id="5" Dir="OUT"/>
			<Port Id="6" Dir="OUT"/>
			<Port Id="7" Dir="OUT"/>
		</Bus>
		<Bus Id="vga_red">
			<Port Id="0" Dir="OUT"/>
			<Port Id="1" Dir="OUT"/>
			<Port Id="2" Dir="OUT"/>
		</Bus>
		<Bus Id="vga_green">
			<Port Id="0" Dir="OUT"/>
			<Port Id="1" Dir="OUT"/>
			<Port Id="2" Dir="OUT"/>
		</Bus>
		<Bus Id="vga_blue">
			<Port Id="0" Dir="OUT"/>
			<Port Id="1" Dir="OUT"/>
		</Bus>
		<Port Id="clk" Dir="IN"/>
		<Port Id="clk40" Dir="IN"/>
		<Port Id="cam_sioc" Dir="OUT"/>
		<Port Id="cam_siod" Dir="INOUT"/>
		<Port Id="cam_reset" Dir="OUT"/>
		<Port Id="cam_pwdn" Dir="OUT"/>
		<Port Id="cam_vsync" Dir="IN"/>
		<Port Id="cam_href" Dir="IN"/>
		<Port Id="cam_pclk" Dir="IN"/>
		<Port Id="cam_xclk" Dir="OUT"/>
		<Port Id="vga_hsync" Dir="OUT"/>
		<Port Id="vga_vsync" Dir="OUT"/>
		<Port Id="btn" Dir="IN"/>
	</Ifc>
</Interface>

